Metadata-Version: 2.1
Name: senseiv2
Version: 0.1
Summary: Sensor Independent Cloud and Shadow Masking with Partial Labels and Multimodal Inputs
Author: Alistair Francis
Author-email: Alistair Francis <alistair.m.francis@gmail.com>
Project-URL: Homepage, https://github.com/aliFrancis/SEnSeIv2
Project-URL: Issues, https://github.com/aliFrancis/SEnSeIv2/issues
Classifier: Programming Language :: Python :: 3
Classifier: License :: OSI Approved :: GNU General Public License v3 (GPLv3)
Classifier: Operating System :: OS Independent
Requires-Python: >=3.9
License-File: LICENSE
Requires-Dist: huggingface-hub >=0.17
Requires-Dist: numpy
Requires-Dist: matplotlib >=3.6.2
Requires-Dist: pyyaml >=6.0
Requires-Dist: rasterio >=1.3.4
Requires-Dist: scikit-image >=0.19.3
Requires-Dist: segmentation-models-pytorch ==0.3.2
Requires-Dist: six
Requires-Dist: torchmetrics >=1.1
Requires-Dist: transformers >=4.34.0
Requires-Dist: wandb >=0.15.12
